CONTRIBUTING.rst
HISTORY.rst
LICENSE
MANIFEST.in
README.rst
setup.cfg
setup.py
docs/Makefile
docs/conf.py
docs/contributing.rst
docs/history.rst
docs/index.rst
docs/installation.rst
docs/make.bat
docs/readme.rst
docs/usage.rst
loadlab/__init__.py
loadlab/cli.py
loadlab/loadlab.py
loadlab.egg-info/PKG-INFO
loadlab.egg-info/SOURCES.txt
loadlab.egg-info/dependency_links.txt
loadlab.egg-info/entry_points.txt
loadlab.egg-info/not-zip-safe
loadlab.egg-info/requires.txt
loadlab.egg-info/top_level.txt
tests/__init__.py
tests/test_loadlab.py