Metadata-Version: 1.1
Name: loadlab
Version: 0.1.0
Summary: Python Cliant for the LoadLab REST API.
Home-page: https://github.com/@iMerica/loadlab
Author: @iMerica
Author-email: imerica@pm.me
License: MIT license
Keywords: loadlab
Platform: UNKNOWN
Classifier: Development Status :: 2 - Pre-Alpha
Classifier: Intended Audience :: Developers
Classifier: License :: OSI Approved :: MIT License
Classifier: Natural Language :: English
Classifier: Programming Language :: Python :: 3.6
Classifier: Programming Language :: Python :: 3.7
